nonebot_plugin_talk_stats/__init__.py
nonebot_plugin_talk_stats/config.py
nonebot_plugin_talk_stats/matcher.py
nonebot_plugin_talk_stats/query.py
nonebot_plugin_talk_stats/render.py
nonebot_plugin_talk_stats/scheduler.py
nonebot_plugin_talk_stats/templates/my.html.jinja2
nonebot_plugin_talk_stats/templates/scene.html.jinja2
nonebot_plugin_talk_stats-0.1.1.dist-info/licenses/LICENSE
nonebot_plugin_talk_stats-0.1.1.dist-info/METADATA
nonebot_plugin_talk_stats-0.1.1.dist-info/WHEEL
nonebot_plugin_talk_stats-0.1.1.dist-info/top_level.txt
nonebot_plugin_talk_stats-0.1.1.dist-info/RECORD
