Metadata-Version: 2.4
Name: nonebot-plugin-talk-stats
Version: 0.1.1
Summary: 群聊活跃度统计插件
Author-email: wyf7685 <wyf7685@162.com>
License-Expression: MIT
Requires-Python: >=3.10
License-File: LICENSE
Requires-Dist: nonebot2>=2.4.0
Requires-Dist: nonebot-plugin-alconna>=0.57.6
Requires-Dist: nonebot-plugin-chatrecorder>=0.7.0
Requires-Dist: nonebot-plugin-htmlrender>=0.6.5
Requires-Dist: nonebot-plugin-orm>=0.7.7
Requires-Dist: nonebot-plugin-uninfo>=0.7.0
Dynamic: license-file
